nice65/__init__.py
nice65/__main__.py
nice65/app.py
nice65-0.1.8.dist-info/LICENSE
nice65-0.1.8.dist-info/METADATA
nice65-0.1.8.dist-info/WHEEL
nice65-0.1.8.dist-info/entry_points.txt
nice65-0.1.8.dist-info/top_level.txt
nice65-0.1.8.dist-info/RECORD
