Metadata-Version: 2.1
Name: nice65
Version: 0.1.8
Summary: Code formatter for CC65 assembly
Author-email: Andrew Dunai <a@dun.ai>
Project-URL: Homepage, https://github.com/and3rson/nice65
Classifier: Programming Language :: Python :: 3
Classifier: License :: OSI Approved :: MIT License
Classifier: Operating System :: OS Independent
Requires-Python: >=3.7
License-File: LICENSE
Requires-Dist: lark (>=1.1.5)
